cs_magic_log/__init__.py
cs_magic_log/logger.py
cs_magic_log-0.1.1.dist-info/METADATA
cs_magic_log-0.1.1.dist-info/WHEEL
cs_magic_log-0.1.1.dist-info/RECORD
